Metadata-Version: 1.0
Name: sycopath
Version: 0.1
Summary: a file system path helper
Home-page: http://github.com/amol9
Author: Amol Umrale
Author-email: babaiscool@gmail.com
License: MIT
Platform: UNKNOWN
